Metadata-Version: 1.0
Name: pyprocessbar
Version: 0.1.32
Summary: 进度显示库
Home-page: https://code.xueersi.com
Author: Ruoyu Wang
Author-email: UNKNOWN
License: UNKNOWN
Platform: UNKNOWN
